tga_safe/__init__.py
tga_safe/query.cpython-38-darwin.so
tga_safe_oper_bsd-0.1.6.dist-info/METADATA
tga_safe_oper_bsd-0.1.6.dist-info/WHEEL
tga_safe_oper_bsd-0.1.6.dist-info/top_level.txt
tga_safe_oper_bsd-0.1.6.dist-info/RECORD
