Metadata-Version: 2.1
Name: tga-safe-oper-bsd
Version: 0.1.6
Summary: A small example package
Home-page: UNKNOWN
Author: yuanxiao
Author-email: yuan6785@163.com
License: UNKNOWN
Platform: UNKNOWN
Classifier: Programming Language :: Python :: 3
Classifier: License :: OSI Approved :: MIT License
Classifier: Operating System :: OS Independent
Requires-Python: >=3.0
Requires-Dist: ezconfig-client==0.7
